pollux_bq/__init__.py
pollux_bq/bq_handler.py
pollux_env/__init__.py
pollux_env/env_manager.py
pypollux-0.0.5.dist-info/LICENSE
pypollux-0.0.5.dist-info/METADATA
pypollux-0.0.5.dist-info/WHEEL
pypollux-0.0.5.dist-info/top_level.txt
pypollux-0.0.5.dist-info/RECORD
